{
    "appName": "cascade",
    "projectId": "83181952-4747-4c74-b385-148bd807f735",
    "version": "2.1.0",
    "isFromSample": false,
    "solutionSettings": {
        "name": "fx-solution-azure",
        "version": "1.0.0",
        "hostType": "Azure",
        "azureResources": [],
        "capabilities": [
            "Tab"
        ],
        "activeResourcePlugins": [
            "fx-resource-frontend-hosting",
            "fx-resource-identity",
            "fx-resource-local-debug",
            "fx-resource-appstudio",
            "fx-resource-cicd",
            "fx-resource-api-connector"
        ]
    },
    "programmingLanguage": "javascript"
}